{
  "id": "aline-barros-retrato-6b320f1621",
  "title": "Retrato",
  "artist": "Aline Barros",
  "collection": "cifras_multi",
  "fileType": "html",
  "key": "A",
  "updatedAt": "2026-04-20T01:59:44.125Z",
  "html": "<u>Intro:  <i>A</i>  <i>F#m</i>  <i>D</i>  <i>E7</i>  <i>A</i>  <i>E7</i>\r\n\r\n</u><u><i>A</i>             <i>E7/G#</i>\r\n</u><u>Uma folha de papel\r\n</u><u>    <i>D</i>            <i>A</i>\r\n</u><u>Um lápis para rabiscar\r\n</u><u><i>D</i>                <i>F#m</i>\r\n</u><u>Eu vou fazer um desenho\r\n</u><u><i>Bm</i>                 <i>E7</i>\r\n</u><u>Tão bonito vai ficar\r\n</u><u><i>A</i>               <i>C#m</i>     <i>D</i>                 <i>A</i>\r\n</u><u>O retrato de alguém     é o que eu vou fazer\r\n</u><u><i>D</i>                <i>A</i>\r\n</u><u>Vai se parecer comigo\r\n</u><u><i>E7</i>                <i>A</i>\r\n</u><u>E quem sabe com você\r\n\r\n</u><u><i>D</i>                     <i>C#m</i>\r\n</u><u>Primeiro eu desenho os olhos\r\n</u><u><i>E7</i>                 <i>A</i>\r\n</u><u>Depois eu faço o nariz\r\n</u><u>   <i>C#</i>           <i>F#m</i>\r\n</u><u>Na boca ponha um sorriso\r\n</u><u>    <i>B7</i>               <i>E7</i>\r\n</u><u>Pro rosto ficar bem feliz\r\n\r\n</u><u><i>A</i>        <i>F#m</i>\r\n</u><u>Alguém prá ser feliz assim\r\n</u><u>         <i>A</i>       <i>Bm</i>\r\n</u><u>Precisa ter uma razão\r\n</u><u>        <i>Bm/A</i>\r\n</u><u>Só pode ser alguém\r\n</u><u>     <i>E7/G#</i>        <i>E7</i>          <i>A</i>\r\n</u><u>Que tem o amor de Deus no coração.\r\n\r\n</u><u>( <i>A</i>  <i>F#m</i>  <i>D</i>  <i>E7</i>  <i>A</i>  <i>E7</i> )</u>"
}