{
  "id": "aline-barros-bem-aventurado-ver-2-564a08ed47",
  "title": "Bem-aventurado (ver. 2)",
  "artist": "Aline Barros",
  "collection": "cifras_multi",
  "fileType": "html",
  "key": "C",
  "updatedAt": "2026-04-20T01:40:12.093Z",
  "html": "<u>INTRO: ||: <i>C/A#</i> <i>A#</i> | <i>C/A#</i> <i>A#</i> | <i>C/F</i> <i>F</i> <i>C/F</i> <i>F</i> :|| 2x\r\n\r\n</u><u>                          <i>C/A#</i>                         <i>A#</i> <i>C/A#</i>                 <i>A#</i>                       <i>C/F</i>   <i>F</i> <i>C/F</i> <i>F</i>\r\n</u><u>BEM AVENTURADO É O QUE ESTÁ                  FIRMADO EM TUA CASA\r\n</u><u>                                 <i>C/A#</i>  <i>A#</i>  <i>Gm7</i>\r\n</u><u>AQUELES QUE TE LOUVAM\r\n</u><u>                           <i>C9</i>                                    <i>F9</i>\r\n</u><u>CUJO O CORAÇÃO ESTÁ NO NOSSO DEUS\r\n</u><u>INTERLÚDIO: || <i>C/E</i> <i>G9</i> | <i>Am7</i> <i>F9</i> | <i>C/E</i> <i>G</i> | <i>Am7</i> <i>F9</i> ||\r\n\r\n</u><u>                          <i>G/F</i>                            <i>F</i> <i>G/F</i>                     <i>F</i>                         <i>G/C</i> <i>C</i> <i>G/C</i> <i>C</i>\r\n</u><u>BEM AVENTURADO É O QUE ESTÁ                  FIRMADO EM TUA CASA\r\n</u><u>                                 <i>G/F</i>       <i>F</i>       <i>Dm7</i>\r\n</u><u>AQUELES QUE TE LOUVAM\r\n</u><u>                           <i>G9</i>                                    <i>C9</i>\r\n</u><u>CUJO O CORAÇÃO ESTÁ NO NOSSO DEUS\r\n\r\n</u><u>                          <i>G/F</i>                        <i>F</i> <i>G/F</i>         <i>F</i>                    <i>G/C</i>             <i>C</i>      <i>G/C</i> <i>C</i>\r\n</u><u>BEM AVENTURADO É O QUE TEM           SEDE DA JUSTIÇA DE DEUS\r\n</u><u>                                 <i>G/F</i>       <i>F</i>       <i>Dm7</i>\r\n</u><u>AQUELES QUE SÃO FILHOS DA LUZ\r\n</u><u>                               <i>G9</i>                         <i>C9</i>\r\n</u><u>CUJA A FORÇA VEM DO NOSSO DEUS\r\n\r\n</u><u>                                   <i>F9</i>                           <i>G9</i>\r\n</u><u>QUE O TEU REINO VENHA SOBRE NÓS\r\n</u><u>                                   <i>F/A</i>                      <i>G4</i> <i>G9</i>\r\n</u><u>QUEREMOS TUA GLÓRIA SOBRE NÓS\r\n\r\n</u><u><i>C9</i>            <i>G9</i>\r\n</u><u>OUVE, Ó DEUS\r\n</u><u>            <i>Am7</i>                   <i>F</i>\r\n</u><u>NOSSA ORAÇÃO, ALTÍSSIMO\r\n</u><u><i>C/E</i>                        <i>G9</i>\r\n</u><u>SARA ESSA NAÇÃO\r\n</u><u>         <i>Am7</i>                              <i>F9</i>               1°, 2° e 3° (ABAIXO)\r\n</u><u>É O CLAMOR DA IGREJA QUE TE ADORA\r\n</u><u>1° <i>G/F</i> <i>F</i> <i>G/F</i> <i>F</i> <i>G/C</i> <i>C</i> <i>G/C</i> <i>C</i>\r\n</u><u>2° <i>G9</i>\r\n</u><u>3° <i>G9</i> <i>C9</i> <i>G/B</i> <i>Am7</i> <i>F</i> <i>C9</i> <i>G/B</i> <i>Am7</i> <i>F9</i>\r\n\r\n</u><u>                 <i>C9</i>\r\n</u><u>SÓ TU ÉS SANTO\r\n</u><u>                 <i>G/B</i>\r\n</u><u>SÓ TU ÉS SANTO\r\n</u><u><i>Am7</i>                                   <i>F</i>\r\n</u><u>SÓ TU ÉS SANTO, SENHOR</u>"
}