{
  "id": "aline-barros-jesus-filho-de-deus-b8d0b056ae",
  "title": "Jesus, filho de deus",
  "artist": "Aline Barros",
  "collection": "cifras_multi",
  "fileType": "html",
  "key": "E",
  "updatedAt": "2026-04-20T01:48:54.973Z",
  "html": "<u>INTRO: <i>Em</i>  <i>C9</i>  <i>G</i>  <i>Bm7</i>\r\n</u><u>      (<i>Em</i>  <i>C9</i>  <i>G</i>  <i>D9</i>)\r\n\r\n</u><u><i>G</i>                  <i>D9</i>\r\n</u><u>   Em minha vida está o Espírito de Deus\r\n</u><u><i>Em7</i>                 <i>C9</i>\r\n</u><u>   Meus lábios o Senhor ungiu pra anunciar\r\n</u><u><i>G</i>                <i>D9</i>              <i>Cm6</i>\r\n</u><u>   As boas novas do Evangelho ao mundo inteiro...\r\n</u><u><i>G</i>               <i>D9</i>\r\n</u><u>   Por ti eu viverei não me envergonharei\r\n</u><u><i>Em7</i>             <i>C9</i>\r\n</u><u>   Preciso revelar ao mundo quem tú és\r\n</u><u><i>G</i>                  <i>D9</i>        <i>Cm6</i>\r\n</u><u>   Falar dessa verdade eterna - Jesus...\r\n\r\n</u><u><i>Em</i>                <i>C9</i>\r\n</u><u>    Quão formosos são os pés daqueles que\r\n</u><u><i>G</i>                 <i>D</i>\r\n</u><u>    Falam do teu Reino e do teu Poder\r\n</u><u><i>Em</i>              <i>C9</i>\r\n</u><u>    Toma minha vida, podes me usar\r\n</u><u><i>G</i>             <i>D9</i>\r\n</u><u>    Com autoridade eu quero declarar\r\n\r\n</u><u><i>Em</i>                        <i>C</i>\r\n</u><u>    Ele é o autor da vida é a própria Salvação\r\n</u><u><i>G</i>                     <i>Bm7</i>\r\n</u><u>    Ele é a única esperança de toda nação\r\n</u><u><i>Em</i>                        <i>C</i>\r\n</u><u>    Foi enviado ao mundo pra salvar você e eu\r\n</u><u><i>G</i>                 <i>D</i>\r\n</u><u>    Jesus, Jesus, o Filho de Deus...\r\n</u><u><i>Em</i>                     <i>C</i>\r\n</u><u>    É a maior riqueza que o homem pode ter\r\n</u><u><i>G</i>                           <i>Bm7</i>\r\n</u><u>    Ele é a porta em que se bate e se encontra a paz\r\n</u><u><i>Em</i>                      <i>C</i>\r\n</u><u>    Uma semente foi lançada pelo próprio Pai\r\n</u><u><i>G</i>                 <i>D</i>\r\n</u><u>    Jesus, Jesus, o Filho de Deus...\r\n\r\n</u><u>REINTRO: <i>Em</i>  <i>C9</i>  <i>G</i>  <i>D9</i>  <i>Em</i>  <i>C9</i>  <i>G</i>  <i>D9</i>\r\n\r\n</u><u>SOLO: <i>Gm7</i>  <i>Eb</i>  <i>Bb</i>  <i>F/A</i>\r\n</u><u>     (<i>Gm7</i>  <i>Eb/G</i>  <i>Bb</i>  <i>Am</i>  <i>Gm</i>  <i>B/F#</i>  <i>B/D#</i>)\r\n\r\n</u><u>FINAL: <i>Em</i>  <i>C9</i>  <i>G</i>  <i>D9</i>  <i>Em</i>  <i>C9</i>  <i>G</i>  <i>D9</i></u>"
}