{
  "id": "aline-barros-noite-de-paz-3f380b6216",
  "title": "Noite de Paz",
  "artist": "Aline Barros",
  "collection": "cifras_multi",
  "fileType": "html",
  "key": "Bb",
  "updatedAt": "2026-04-20T01:54:16.892Z",
  "html": "<u>[Intro] <i>Bb2</i>  <i>F/A</i>  <i>D#/G</i>  <i>D/F#</i>\r\n</u><u>        <i>Gm7</i>  <i>Cm9</i>  <i>F#5+</i>  <i>Bb/F</i>  <i>F</i>\r\n</u><u>        <i>D#/G</i>  <i>F/A</i>  <i>D#/A#</i>  <i>D#m/A#</i>  <i>A#</i>\r\n\r\n</u><u>[Primeira Parte]\r\n\r\n</u><u><i>F</i> <i>Bb</i>\r\n</u><u>  Noite de paz, noite de amor\r\n</u><u><i>Bb/C</i> <i>F7</i>   <i>D/F#</i>  <i>Gm</i>   <i>Fm7</i>  <i>Bb</i>  <i>Cm</i>  <i>Bb/D</i>\r\n</u><u>     Tudo dorme em redor\r\n</u><u><i>D#</i>           <i>Dm</i> <i>F/C</i>      <i>Bb/D</i>   <i>F/C</i> <i>Bb</i>\r\n</u><u>Entre os astros    que espargem a   luz\r\n\r\n</u><u>( <i>Bb</i>  <i>Cm</i>  <i>Bb/D</i> )\r\n\r\n</u><u><i>D#</i>        <i>Dm</i> <i>F/C</i> <i>Bb</i> <i>F/C</i> <i>Gm7</i>  <i>Bb/C</i>\r\n</u><u>Proclamando  o menino Jesus\r\n</u><u><i>D#/F</i>       <i>Am7(5-)</i> <i>D9-</i> <i>Gm</i>  <i>C7(13)</i>\r\n</u><u>Brilha a estrela   da  paz\r\n</u><u><i>D#m/F#</i>  <i>Bb/F</i>       <i>F</i>     <i>F/A</i> <i>Bb</i>  <i>Eb/Bb</i>  <i>Bb</i>\r\n</u><u>        Brilha a estrela da  paz\r\n\r\n</u><u>[Segunda Parte]\r\n\r\n</u><u><i>Bb</i>                      <i>Gm7</i>  <i>Bb/C</i>\r\n</u><u>Noite de paz, noite de amor\r\n</u><u><i>F7</i>     <i>D/F#</i> <i>C/E</i> <i>D</i> <i>Gm</i>    <i>Fm/Bb</i>\r\n</u><u>Nas campinas,     ao pastor\r\n</u><u><i>D#</i>                <i>Bb/D</i>    <i>Bb</i>  <i>G#/C</i>  <i>Bb7/D</i>\r\n</u><u>Lindos anjos mandados por Deus\r\n</u><u><i>D#</i>     <i>Dm</i> <i>F/C</i>  <i>Bb/D</i> <i>F/C</i> <i>Gm7</i>  <i>Bb/C</i>\r\n</u><u>Anunciam     a nova dos céus\r\n</u><u><i>F7</i>      <i>Am7(5-)</i> <i>D9-</i> <i>Gm</i>  <i>C7(13)</i>\r\n</u><u>Nasce o bom  Salva__dor\r\n</u><u><i>D#m/F#</i> <i>Bb/F</i>    <i>F</i>   <i>F#°</i>  <i>Gm</i>\r\n</u><u>       Nasce o bom Salvador\r\n\r\n</u><u>[Ponte] <i>Am7(5-)</i>  <i>D9-</i>  <i>Fm7</i>  <i>Bb7</i>\r\n\r\n</u><u><i>Final</i>\r\n\r\n</u><u>            <i>Bb/D#</i>  <i>G#/F#</i>\r\n</u><u>A paz do Senhor\r\n</u><u><i>Bb/F</i> <i>C7</i> <i>Am7(5-)</i> <i>D9-</i>  <i>Fm7</i>  <i>Bb7</i>\r\n</u><u>Paz, paz,      paz\r\n</u><u>            <i>Bb/D#</i>  <i>D#m/F#</i>\r\n</u><u>A paz do Senhor\r\n</u><u><i>Bb/F</i>      <i>Am7(5-)</i>  <i>D9-</i>\r\n</u><u>    Rei, Rei\r\n</u><u><i>Gm</i>       <i>C7</i>\r\n</u><u>Oh, Salvador!\r\n</u><u><i>Bb/F</i>    <i>F7</i>       <i>D#/A#</i>  <i>A#</i>\r\n</u><u>Nasce o bom Salvador</u>"
}