{
  "id": "asaph-borba-enche-me-de-ti-18e993df65",
  "title": "Enche-me de ti",
  "artist": "Asaph Borba",
  "collection": "cifras_multi",
  "fileType": "html",
  "key": "D",
  "updatedAt": "2026-04-26T12:01:37.955Z",
  "html": "<u>INT.:  <i>D9</i>  <i>G9</i>  <i>Em7</i>  <i>G9</i>  <i>A4</i> (2x)\r\n\r\n</u><u>  <i>D9</i>                 <i>A/C#</i>             <i>Bm7</i>    <i>G9</i>                  <i>A4</i>    <i>Bm7</i>\r\n</u><u>  Enche-me de Ti Senhor Jesus  -  Enche-me de Ti Senhor\r\n</u><u>   <i>G9</i>                                 <i>D/F#</i>\r\n</u><u>  Seja minha vida um manancial\r\n</u><u>                       <i>C9</i>                <i>Em7</i>    <i>A4</i>     <i>A</i>\r\n</u><u>  Sempre a jorrar Teu precioso amor\r\n\r\n</u><u>                       <i>Em7</i>                <i>A</i>       <i>D9</i>     <i>A/C#</i>\r\n</u><u>  Sempre a jorrar Teu precioso amor\r\n\r\n</u><u>   <i>Bm7</i>                      <i>F#m7</i>        <i>G</i>                <i>A</i>        <i>D9</i>   <i>A/C#</i>\r\n</u><u>  Rios de água viva fluirão  -  Para vidas restaurar\r\n</u><u>   <i>Bm7</i>                       <i>F#m7</i>         <i>G</i>                                           <i>A4</i>     <i>A</i>\r\n</u><u>  Ossos secos ressuscitarão  -  Quando a água sobre eles jorrar\r\n\r\n\r\n</u><u>  Enche-me de Ti Senhor Jesus... (2x)\r\n\r\n</u><u>   <i>Bm7</i>                            <i>F#m7</i>   <i>G</i>                 <i>A</i>              <i>D9</i>   <i>A/C#</i>\r\n</u><u>  Todo aquele que tem sede  -  Desta água poderá beber\r\n</u><u>   <i>Bm7</i>                      <i>F#m7</i>            <i>G</i>                                <i>A4</i>    <i>A</i>\r\n</u><u>  Todo aquele que assim fizer  - Sede nunca mais vai ter\r\n\r\n</u><u>        <i>F#4</i>  <i>F#7</i>  <i>Bm</i>         <i>F#4</i>  <i>F#7</i>  <i>G9</i>   <i>D/F#</i>\r\n</u><u>  Eu tenho        sede, eu tenho       sede\r\n</u><u>  <i>Em7</i>     <i>A</i>      <i>Bm</i>     <i>G9</i>  <i>Em7</i>   <i>F#m7</i> <i>F#7</i>  <i>Bm</i>\r\n</u><u>  Dá-me de beber Jesus, dá-me de beber\r\n</u><u>                                                             (<i>G9</i>  <i>A4</i>  <i>A</i>) última vez!\r\n\r\n</u><u>    <i>D9</i>                 <i>A/C#</i>             <i>Bm7</i>    <i>G9</i>                  <i>A4</i>    <i>Bm7</i>\r\n</u><u>  Enche-me de Ti Senhor Jesus  -  Enche-me de Ti Senhor\r\n</u><u>   <i>G9</i>                                 <i>D/F#</i>\r\n</u><u>  Seja minha vida um manancial\r\n</u><u>                       <i>C9</i>                <i>Em7</i>    <i>A4</i>     <i>A</i>\r\n</u><u>  Sempre a jorrar Teu precioso amor\r\n\r\n</u><u>                       <i>Em7</i>                <i>A</i>       <i>D9</i>    <i>G9</i>  <i>Em7</i>  <i>G9</i>  <i>A4</i>   <i>D9</i>\r\n</u><u>  Sempre a jorrar Teu precioso amor</u>"
}