{
  "id": "eli-soares-ninguem-explica-deus-534682ceb9",
  "title": "Ninguém Explica Deus",
  "artist": "Eli Soares",
  "collection": "cifras_multi",
  "fileType": "html",
  "key": "A",
  "updatedAt": "2026-04-20T00:59:29.509Z",
  "html": "<u><i>A7M</i>                      <i>G#m7(11)</i>\r\n</u><u>Nada é igual ao Seu redor\r\n</u><u><i>F#m7(11)</i>                 <i>C#m7</i>\r\n</u><u>Tudo se faz no Seu olhar\r\n</u><u><i>D7M</i>            <i>C#m7</i>           <i>Bm7</i>  <i>D9/F#</i> <i>E/G#</i>\r\n</u><u>O universo se formou no Seu falar\r\n</u><u><i>A7M</i>                  <i>G#m7(11)</i>\r\n</u><u>Teologia pra explicar\r\n</u><u><i>F#m7(11)</i>                <i>C#m7</i>\r\n</u><u>Ou Big Bang pra disfarçar\r\n</u><u><i>D7M</i>                 <i>C#m7</i>\r\n</u><u>Pode alguém até duvidar\r\n</u><u> <i>D9/F#</i>                    <i>E/G#</i> <i>C#m7</i>\r\n</u><u>Sei que há um Deus a me guardar\r\n</u><u><i>D7M</i>          <i>E/D</i>             <i>F#m7(11)</i>\r\n</u><u>E eu, tão pequeno e frágil, querendo Sua atenção\r\n</u><u><i>Bm7</i>      <i>C#m7</i>           <i>D9/G</i>          <i>E/G#</i>\r\n</u><u>No silêncio encontro resposta certa, então\r\n</u><u><i>A7M</i>           <i>G#m7(11)</i>  <i>F#m7(11)</i>         <i>C#m7</i>\r\n</u><u>Dono de toda ciência,            sabedoria e poder\r\n</u><u><i>D7M</i>           <i>C#m7</i>     <i>Bm7</i>       <i>D9/F#</i> <i>E/G#</i>\r\n</u><u>Oh, dá-me de beber da água da fonte da vida\r\n</u><u><i>A7M</i>           <i>G#m7(11)</i>   <i>F#m7(11)</i>\r\n</u><u>Antes que o haja houvesse\r\n</u><u>         <i>C#m7</i>\r\n</u><u>Ele já era Deus\r\n</u><u><i>D7M</i>          <i>C#m7</i>\r\n</u><u>Se revelou ao seus\r\n</u><u><i>Bm7</i>           <i>E/G#</i>\r\n</u><u>Do gentio ao judeu\r\n</u><u><i>A7M</i>\r\n</u><u>Ninguém explica Deus\r\n</u><u><i>A7M</i>\r\n</u><u>Ninguém explica\r\n</u><u> <i>G#m7(11)</i>  <i>F#m7(11)</i>\r\n</u><u>Ninguém explica Deus\r\n\r\n</u><u>Ninguém explica\r\n</u><u>    <i>C#m7</i>\r\n</u><u>Ninguém explica Deus\r\n</u><u><i>D7M</i>                <i>C#m7</i>\r\n</u><u>E se duvida ou se acredita\r\n</u><u>         <i>Bm7</i>\r\n</u><u>Ninguém explica\r\n</u><u> <i>E/G#</i>\r\n</u><u>Ninguém explica Deus\r\n</u><u><i>D7M</i>                 <i>C#m7</i>\r\n</u><u>E se duvida ou se acredita\r\n</u><u>        <i>Bm7</i>\r\n</u><u>Ninguém explica\r\n</u><u>         <i>E/G#</i>    <i>A7M</i>\r\n</u><u>Ninguém explica Deus\r\n\r\n</u><u><i>A7M</i>           <i>G#m7(11)</i>  <i>F#m7(11)</i>         <i>C#m7</i>\r\n</u><u>Dono de toda ciência,            sabedoria e poder\r\n</u><u><i>D7M</i>           <i>C#m7</i>     <i>Bm7</i>       <i>D9/F#</i> <i>E/G#</i>\r\n</u><u>Oh, dá-me de beber da água da fonte da vida\r\n</u><u><i>A7M</i>           <i>G#m7(11)</i>   <i>F#m7(11)</i>\r\n</u><u>Antes que o haja houvesse\r\n</u><u>         <i>C#m7</i>\r\n</u><u>Ele já era Deus\r\n</u><u><i>D7M</i>          <i>C#m7</i>\r\n</u><u>Se revelou ao seus\r\n</u><u><i>Bm7</i>           <i>E/G#</i>\r\n</u><u>Do gentio ao judeu\r\n</u><u><i>A7M</i>\r\n</u><u>Ninguém explica Deus</u>"
}