{
  "id": "eli-soares-nao-me-deixe-ir-4a2835f957",
  "title": "Não Me Deixe Ir",
  "artist": "Eli Soares",
  "collection": "cifras_multi",
  "fileType": "html",
  "key": "C",
  "updatedAt": "2026-04-20T01:00:06.283Z",
  "html": "<u>[Intro] <i>C</i>  <i>D</i>  <i>C</i>  <i>D</i>  <i>Em</i>  <i>D</i>\r\n\r\n</u><u>       <i>G</i>\r\n</u><u>Não me deixe ir\r\n</u><u>               <i>D</i>       <i>C</i>\r\n</u><u>Se tua presença não me acompanhar\r\n</u><u>       <i>G</i>\r\n</u><u>Não me deixe aqui\r\n</u><u>                   <i>C</i>\r\n</u><u>Se tua presença é o meu lugar\r\n</u><u>            <i>Am</i>\r\n</u><u>De que vale ter sucesso\r\n</u><u>              <i>D</i>\r\n</u><u>Do que adianta todo o mérito\r\n</u><u>    <i>Em</i>\r\n</u><u>Se o senhor não estiver\r\n</u><u>         <i>Am</i>\r\n</u><u>É que eu não sei andar sozinho\r\n</u><u>         <i>D</i>\r\n</u><u>Não abro mão, não negocio a tua presença\r\n</u><u><i>Em</i>\r\n</u><u>Em mim\r\n</u><u>      <i>D</i>\r\n</u><u>A tua presença em mim\r\n</u><u>       <i>C</i>\r\n</u><u>Não me deixe ir\r\n</u><u>       <i>Em</i>        <i>D</i>\r\n</u><u>Sem me acompanhar\r\n</u><u>       <i>C</i>\r\n</u><u>Não me deixe aqui\r\n</u><u>  <i>Em</i>           <i>D</i>\r\n</u><u>Fica comigo\r\n\r\n</u><u>          <i>Am</i>\r\n</u><u>De que vale ter sucesso\r\n</u><u>               <i>D</i>\r\n</u><u>Do que adianta todo o mérito\r\n</u><u>     <i>Em</i>\r\n</u><u>Se o senhor não estiver\r\n</u><u>                <i>Am</i>\r\n</u><u>É que eu não sei andar sozinho\r\n</u><u>          <i>D</i>                      <i>Em</i>\r\n</u><u>Não abro mão, não negocio a tua presença\r\n</u><u>Em mim\r\n</u><u>      <i>D</i>\r\n</u><u>A tua presença em mim\r\n\r\n</u><u>       <i>C</i>\r\n</u><u>Não me deixe ir\r\n</u><u>        <i>Em</i>       <i>D</i>\r\n</u><u>Sem me acompanhar\r\n</u><u>            <i>C</i>\r\n</u><u>Não me deixe aqui\r\n</u><u>     <i>Em</i>     <i>D</i>\r\n</u><u>Fica comigo\r\n</u><u>            <i>C</i>\r\n</u><u>Não me deixe ir\r\n</u><u>            <i>Em</i>     <i>D</i>\r\n</u><u>Sem me acompanhar\r\n</u><u>            <i>C</i>\r\n</u><u>Não me deixe aqui\r\n</u><u> <i>Em</i>\r\n</u><u>Fica comigo\r\n</u><u>        <i>D</i>\r\n</u><u>Meu Deus, fica comigo\r\n</u><u><i>C</i>       <i>D</i>          <i>E</i>\r\n</u><u>Ooh    Ooh       Ooooooh\r\n</u><u>  <i>Bm</i>           <i>C</i>        <i>D</i>\r\n</u><u>Ooooooh        ooh      Ooh\r\n</u><u><i>C</i> <i>D</i> <i>E</i>\r\n</u><u>Ooooooh\r\n\r\n</u><u>       <i>C</i>\r\n</u><u>Não me deixe ir\r\n</u><u>        <i>Em</i>       <i>D</i>\r\n</u><u>Sem me acompanhar\r\n</u><u>        <i>C</i>\r\n</u><u>Não me deixe aqui\r\n</u><u>         <i>Em</i>      <i>D</i>\r\n</u><u>Fica comigo</u>"
}