{
  "id": "eyshila-exemplo-de-mae-d47424b847",
  "title": "Exemplo De Mãe",
  "artist": "Eyshila",
  "collection": "cifras_multi",
  "fileType": "html",
  "key": "D",
  "updatedAt": "2026-04-26T12:57:43.602Z",
  "html": "<u>(intro) <i>D</i>  <i>F#m</i>  <i>G</i>\r\n</u><u>        <i>D</i>  <i>F#m</i>  <i>G</i>  <i>G/Bb</i>\r\n\r\n</u><b>E|------17-17-------17-17--------12-14-15-14-12-------17--17-------17-17------|\r\n</b><b>B|--15--------15-14-------14-12----------------14-15---------15-14-------14-12|\r\n</b><b>G|----------------------------------------------------------------------------|\r\n</b><b>D|----------------------------------------------------------------------------|\r\n</b><b>A|----------------------------------------------------------------------------|\r\n</b><b>E|----------------------------------------------------------------------------|\r\n\r\n</b><b>E|-12-14-15-14-10---12-14-14-14-10-|\r\n</b><b>B|---------------------------------|\r\n</b><b>G|---------------------------------|\r\n</b><b>D|---------------------------------|\r\n</b><b>A|---------------------------------|\r\n</b><b>E|---------------------------------|\r\n\r\n</b><u><i>D</i>          <i>F#m</i>\r\n</u><u>Mãe, quer dizer amor\r\n</u><u><i>Bm</i>         <i>D7</i>\r\n</u><u>Mãe, quer dizer pureza\r\n</u><u><i>G</i>         <i>D/F#</i>\r\n</u><u>Mãe, sabe quem eu sou\r\n</u><u>   <i>Em</i>          <i>G</i>     <i>G/Bb</i>\r\n</u><u>E acha que eu sou perfeita\r\n\r\n</u><u><i>D</i>          <i>F#m</i>\r\n</u><u>Mãe, quer dizer carinho\r\n</u><u><i>Bm</i>         <i>D7</i>\r\n</u><u>Mãe, quer dizer beijinho\r\n</u><u><i>G</i>             <i>D/F#</i>      <i>A4</i> <i>A</i>   <i>Em7</i>\r\n</u><u>Mãe, me faz sentir especial\r\n\r\n</u><u>                                <i>G</i>\r\n</u><u>Quantas vezes eu não te escutei\r\n</u><u>                          <i>D</i>\r\n</u><u>E escolhi os meus caminhos\r\n</u><u>                          <i>A4</i>  <i>A</i>  <i>Em7</i>\r\n</u><u>Mas você não desistiu de mim\r\n</u><u>                        <i>G</i>\r\n</u><u>Você sempre viu muito além\r\n</u><u>                              <i>D</i>\r\n</u><u>Do que os outros conseguiram ver\r\n</u><u>                    <i>A4</i>      <i>A</i>\r\n</u><u>E porque você orou, eu venci\r\n\r\n</u><u><i>D/F#</i>\r\n</u><u>Mãe, eu não te mereço\r\n</u><u><i>F#m</i>\r\n</u><u>Mãe, eu te agradeço\r\n</u><u><i>G</i>     <i>D/F#</i>\r\n</u><u>Mãe, você não tem preço\r\n</u><u><i>Em</i>           <i>A</i>\r\n</u><u>Mãe, você é tudo de bom\r\n</u><u><i>D/F#</i>\r\n</u><u>Mãe, você é tão bonita\r\n</u><u><i>F#m</i>\r\n</u><u>Mãe, amor da minha vida\r\n</u><u><i>G</i>           <i>D/F#</i>\r\n</u><u>Mãe, minha melhor amiga\r\n</u><u><i>Em</i>        <i>A</i>\r\n</u><u>Quem te conhece te quer\r\n</u><u><i>G/Bb</i>                                  <i>A</i>    <i>D</i>\r\n</u><u>Mãe, você pra mim é o melhor exemplo de mulher </u>"
}