{
  "id": "felipe-rodrigues-nao-quero-ser-mais-um-e934238441",
  "title": "Não quero ser mais um",
  "artist": "Felipe Rodrigues",
  "collection": "cifras_multi",
  "fileType": "html",
  "key": "A",
  "updatedAt": "2026-04-20T01:02:19.354Z",
  "html": "<u>Intro: <i>Am</i>  <i>G</i>  <i>C/E</i>  <i>F</i>\r\n\r\n</u><u><i>Am</i>              <i>G</i>                                  <i>F</i>\r\n</u><u>Eu já decidi,não quero mais viver por mim,fazer minhas vontades\r\n</u><u><i>Am</i>                    <i>G</i>\r\n</u><u>pois já não vivo eu, é cristo quem vive em mim\r\n</u><u>          <i>F</i>                       <i>Dm</i>\r\n</u><u>eu vivo a verdade, não quero ser mais um\r\n\r\n</u><u>Intro: ( <i>Am</i>  <i>G</i>  <i>C/E</i>  <i>F</i> )\r\n\r\n</u><u>Refrão:\r\n</u><u>        <i>C</i>                   <i>G</i>\r\n</u><u>Eu quero ser segundo o teu coração\r\n</u><u>          <i>Am</i>                      <i>F</i>\r\n</u><u>andar na tua direção,fazer somente tua vontade\r\n</u><u>          <i>C</i>                     <i>G</i>\r\n</u><u>não quero ser mais um em meio a multidão\r\n</u><u>           <i>Am</i>                   <i>F</i>\r\n</u><u>preciso da tua unção, pra diferença eu fazer\r\n\r\n</u><u>Solo 2x: ( <i>Am</i>  <i>G</i>  <i>F</i> )\r\n\r\n</u><u>        <i>C</i>                   <i>G</i>\r\n</u><u>Eu quero ser segundo o teu coração\r\n</u><u>          <i>Am</i>                    <i>F</i>\r\n</u><u>andar na tua direção,fazer somente tua vontade\r\n</u><u>          <i>C</i>                      <i>G</i>\r\n</u><u>não quero ser mais um em meio a multidão\r\n</u><u>              <i>Am</i>        <i>G</i>         <i>F</i>\r\n</u><u>preciso da tua unção, pra diferença eu fazer</u>"
}