{
  "id": "fernandinho-castelo-forte-cdfad77301",
  "title": "Castelo Forte",
  "artist": "Fernandinho",
  "collection": "cifras_multi",
  "fileType": "html",
  "key": "B",
  "updatedAt": "2026-04-20T00:24:17.542Z",
  "html": "<u>[Intro] <i>Bm7</i>  <i>G</i>  <i>D</i>\r\n\r\n</u><u><i>Bm7</i>     <i>C#m7</i>          <i>D</i>\r\n</u><u>Castelo forte é nosso Deus\r\n</u><u><i>Bm</i>       <i>A/C#</i>    <i>D</i>  <i>Em7</i>\r\n</u><u>Espada e bom escudo\r\n</u><u><i>Bm7</i>       <i>A/C#</i>            <i>D</i>\r\n</u><u>Com seu poder defende os seus\r\n</u><u><i>Bm</i>       <i>A/C#</i>     <i>D</i>  <i>G</i>\r\n</u><u>Em todo transe agudo\r\n\r\n</u><u>     <i>D</i>\r\n</u><u>Com fúria pertinaz\r\n</u><u>    <i>G</i>\r\n</u><u>Persegue Satanás\r\n</u><u>    <i>Em</i>\r\n</u><u>Com artimanhas tais\r\n</u><u>    <i>Bm</i>\r\n</u><u>E astúcias tão cruéis\r\n</u><u>      <i>G</i>                     <i>D</i>\r\n</u><u>Que iguais não há na terra\r\n\r\n</u><u><i>Bm7</i>     <i>A/C#</i>        <i>D</i>\r\n</u><u>A nossa força nada faz\r\n</u><u><i>Bm7</i>     <i>C#m7</i>        <i>D</i>  <i>Em7</i>\r\n</u><u>Estamos, sim, perdidos\r\n</u><u><i>Bm7</i>       <i>C#m7</i>          <i>D</i>\r\n</u><u>Mas nosso Deus socorro traz\r\n</u><u><i>Bm7</i>     <i>A/C#</i>   <i>D</i>   <i>G</i>\r\n</u><u>E somos protegidos\r\n\r\n</u><u>   <i>E7</i>        <i>D</i>\r\n</u><u>Defende-nos Jesus\r\n</u><u>   <i>G</i>\r\n</u><u>O que venceu na cruz\r\n</u><u>   <i>Em</i>\r\n</u><u>Senhor dos altos céus\r\n</u><u>   <i>Bm</i>\r\n</u><u>E sendo o próprio Deus\r\n</u><u>   <i>G</i>               <i>D</i>\r\n</u><u>Triunfa na batalha\r\n\r\n</u><u><i>Bm7</i>       <i>A/C#</i>        <i>D</i>\r\n</u><u>Se nos quisessem devorar\r\n</u><u><i>Bm7</i>      <i>A/C#</i>     <i>D</i>   <i>Em7</i>\r\n</u><u>Demônios não contados\r\n</u><u><i>Bm7</i>       <i>A</i>         <i>D</i>\r\n</u><u>Não nos podiam assustar\r\n</u><u><i>Bm7</i>        <i>A</i>   <i>D</i>     <i>G</i>\r\n</u><u>Nem somos derrotados\r\n\r\n</u><u>  <i>E7</i>        <i>D</i>\r\n</u><u>O grande acusador\r\n</u><u>     <i>G</i>\r\n</u><u>Dos servos do Senhor\r\n</u><u>   <i>Em</i>\r\n</u><u>Já condenado está\r\n</u><u>   <i>Bm</i>\r\n</u><u>Vencido cairá\r\n</u><u>     <i>G</i>            <i>D</i>\r\n</u><u>Por uma só palavra\r\n\r\n</u><u><i>Bm</i>           <i>A</i>         <i>D</i>\r\n</u><u>Sim, que a palavra ficará\r\n</u><u><i>Bm</i>      <i>A/C#</i>     <i>D</i>  <i>Em7</i>\r\n</u><u>Sabemos com certeza\r\n</u><u><i>Bm</i>     <i>A</i>          <i>D</i>\r\n</u><u>E nada nos assustará\r\n</u><u><i>Bm7</i>         <i>A</i>   <i>D</i>     <i>G</i>\r\n</u><u>Com Cristo por defesa\r\n\r\n</u><u>   <i>D</i>\r\n</u><u>Se temos de perder\r\n</u><u>   <i>G</i>\r\n</u><u>Os filhos, bens, mulher\r\n</u><u>  <i>Em</i>\r\n</u><u>Embora a vida vá\r\n</u><u>    <i>Bm</i>\r\n</u><u>Por nós Jesus está\r\n</u><u>   <i>G</i>                 <i>D</i>\r\n</u><u>E dar-nos-á seu Reino\r\n\r\n</u><u>   <i>G</i>             <i>A</i>    <i>D</i>\r\n</u><u>E dar-nos-á seu Reino</u>"
}