{
  "id": "grupo-logos-o-trenzinho-e44d59d56f",
  "title": "O Trenzinho",
  "artist": "Grupo Logos",
  "collection": "cifras_multi",
  "fileType": "html",
  "key": "E",
  "updatedAt": "2026-04-20T15:57:22.090Z",
  "html": "<u>[Intro] <i>E7</i>  <i>D</i>  <i>A/C#</i>  <i>Bm7</i>\r\n</u><u>        <i>A</i>  <i>A7M</i>  <i>A7</i>\r\n</u><u>        <i>D</i>  <i>D7M</i>  <i>D#º</i>\r\n</u><u>        <i>A</i>  <i>C#7</i>  <i>F#m</i>  <i>F#</i>\r\n</u><u>        <i>B7</i>  <i>E4</i>  <i>E</i>  <i>A</i>  <i>D/E</i>\r\n\r\n</u><u>       <i>A</i>                      <i>A7M</i>   <i>A7</i>\r\n</u><u>O trenzinho que caminha pelo trilho\r\n</u><u>       <i>D</i>                           <i>D7M</i>  <i>D#º</i>\r\n</u><u>Vai depressa, até chegar no seu destino\r\n</u><u>          <i>A</i>               <i>C#7</i>        <i>F#m</i>\r\n</u><u>Cruza os montes, cruza os vales e campinas\r\n</u><u>      <i>B7</i>                       <i>E4</i>  <i>E</i>\r\n</u><u>Sem o trilho sabe que não chegará\r\n\r\n</u><u>     <i>A</i>                     <i>A7M</i>  <i>A7</i>\r\n</u><u>Semelhante é a vida do cristão\r\n</u><u>        <i>D</i>                     <i>D7M</i>  <i>D#º</i>\r\n</u><u>Que tem a palavra no seu coração\r\n</u><u>    <i>A</i>         <i>C#7</i>         <i>F#m</i>\r\n</u><u>Ela é o guia para o seu caminho\r\n</u><u>        <i>B7</i>                         <i>E4</i>  <i>E</i>\r\n</u><u>Como o trilho também é para o trenzinho\r\n\r\n</u><u>     <i>D7M</i>                  <i>D#º</i>\r\n</u><u>É preciso na palavra meditar\r\n</u><u>     <i>A</i>          <i>C#7</i>      <i>F#m</i>  <i>D#º</i>\r\n</u><u>E também nas promessas crer\r\n</u><u>       <i>D7M</i>           <i>D#º</i>\r\n</u><u>Para o que Jesus ensinou\r\n</u><u>   <i>B7</i>       <i>E4</i>  <i>E</i>  <i>D/E</i>\r\n</u><u>Podermos viver</u>"
}