{
  "id": "jefferson-suellen-volta-ja-40ea1b0eb0",
  "title": "Volta Já!",
  "artist": "Jefferson Suellen",
  "collection": "cifras_multi",
  "fileType": "html",
  "key": "A",
  "updatedAt": "2026-04-20T01:20:18.622Z",
  "html": "<u>[Intro] <i>Am</i>  <i>F</i>  <i>C</i>  <i>G</i>\r\n\r\n</u><u><i>Am</i>                            <i>F</i>\r\n</u><u>Você desanimou, e então se afastou\r\n</u><u><i>C</i>               <i>G</i>\r\n</u><u>Da casa do Pai saiu\r\n</u><u><i>Am</i>                     <i>F</i>\r\n</u><u>Achou que era bom, o mundo te enganou\r\n</u><u><i>C</i>             <i>G</i>\r\n</u><u>Mas só se iludiu\r\n\r\n</u><u><i>F</i> <i>G</i>    <i>Am</i>           <i>C</i>             <i>G</i>\r\n</u><u>Vol-ta Já! O pai de braço aberto está\r\n</u><u><i>F</i>   <i>G</i>   <i>Am</i>          <i>C</i>      <i>G</i>\r\n</u><u>Vol-ta já! Vem correndo recomeçar\r\n\r\n</u><u>[Refrão]\r\n\r\n</u><u><i>F</i>                     <i>C</i>                 <i>Am</i>\r\n</u><u>Vem de braço aberto está, o Pai a te esperar\r\n\r\n</u><u><i>G</i>                                      <i>F</i>\r\n</u><u>Ele quer te abraçar, pois te ama e te diz: vem!\r\n</u><u><i>C</i>                             <i>Am</i>\r\n</u><u>Estou a te chamar, e vou te perdoar\r\n</u><u><i>G</i>\r\n</u><u>Não vou te abandonar, és meu Filho\r\n\r\n</u><u><i>C</i>     <i>F</i>\r\n</u><u>Oh oh oh\r\n</u><u><i>C</i>     <i>G</i>\r\n</u><u>Oh oh oh\r\n\r\n</u><u><i>C</i>              <i>F</i>\r\n</u><u>Volta já! volta já!\r\n</u><u><i>C</i>                                    <i>G</i>\r\n</u><u>Vem correndo, o Pai quer muito te abraçar</u>"
}