{
  "id": "michelle-nascimento-jesus-venceu-66c774d338",
  "title": "Jesus venceu",
  "artist": "Michelle Nascimento",
  "collection": "cifras_multi",
  "fileType": "html",
  "key": "C#",
  "updatedAt": "2026-04-23T15:46:54.729Z",
  "html": "<u>    <i>C#m</i>                                <i>A</i>\r\n</u><u>Bendito seja o nome do cordeiro que venceu\r\n</u><u>   <i>E</i>                                <i>B</i>\r\n</u><u>A morte fria e angustiada Ele enfrentou\r\n</u><u><i>F#m</i>                         <i>E/G#</i> <i>A</i>\r\n</u><u>Cravos e espinhos, açoitado Ele foi\r\n</u><u> <i>E</i>                         <i>B</i>\r\n</u><u>Na cruz se fez maldito por mim\r\n</u><u><i>C#m</i>                                     <i>A</i>\r\n</u><u>Entregue a mão de homens malfeitores foi Jesus\r\n</u><u>       <i>E</i>                                     <i>B</i>\r\n</u><u>Sem pecado mesmo assim foi maltratado lá na cruz\r\n</u><u> <i>F#m</i>                          <i>E/G#</i>        <i>A</i>\r\n</u><u>Zombado, criticado, ofendido sem ter merecido\r\n</u><u>     <i>E</i>                      <i>B</i>\r\n</u><u>Sua carne foi marcada pela dor\r\n</u><u> <i>F#m</i>                 <i>A</i>                      <i>E</i>   <i>E4</i> <i>E</i>\r\n</u><u>Mas não se entregou mesmo Ele sofrendo no caminho\r\n</u><u><i>F#</i>              <i>A</i>                     <i>B</i>    <i>F#</i> <i>G#</i> <i>A</i>  <i>B</i>\r\n</u><u>Nem se queixou, aguentou calado os espinhos\r\n\r\n</u><u>          <i>E</i>                 <i>B</i>\r\n</u><u>Jesus venceu o calvário de dor\r\n</u><u>           <i>F#m</i>                  <i>C#m</i>        <i>B</i>\r\n</u><u>Tudo pelo amor que sentiu por você e por mim\r\n</u><u>     <i>E</i>          <i>A</i>          <i>B</i>\r\n</u><u>Defendeu nossa causa e ganhou\r\n</u><u>           <i>F#m</i>                 <i>A</i>        <i>B</i>     <i>E</i>\r\n</u><u>Tudo Ele pagou com seu sangue a vida me deu\r\n\r\n</u><u>        <i>C#m</i>\r\n</u><u>A pedra foi removida o véu se rasgou\r\n</u><u>     <i>B</i>\r\n</u><u>Todo olho humano então contemplou\r\n</u><u>         <i>F#m</i>\r\n</u><u>Que era realidade a mais pura verdade\r\n</u><u>        <i>C#m</i>              <i>B</i>\r\n</u><u>Jesus o Filho de Deus Ele ressuscitou</u>"
}