{
  "id": "oficina-g3-valeria-c6d0fc98b1",
  "title": "Valéria",
  "artist": "Oficina G3",
  "collection": "cifras_multi",
  "fileType": "html",
  "key": "G",
  "updatedAt": "2026-04-21T23:56:27.844Z",
  "html": "<u>Intro: <i>G</i> <i>F</i> <i>C</i>\r\n</u><u>       <i>G</i> <i>F</i> <i>E</i>\r\n\r\n</u><u><i>G</i>         <i>F</i>                       <i>C</i>\r\n</u><u>Valéria vivia muito bem com seus pais\r\n\r\n</u><u><i>G</i>         <i>F</i>         <i>E</i>\r\n</u><u>Até que brigas separação\r\n\r\n</u><u><i>G</i>              <i>F</i>        <i>C</i>      <i>G</i>   <i>F</i>       <i>E</i>\r\n</u><u>Morar com as amigas solução faculdade capital\r\n\r\n</u><u><i>G</i>             <i>F</i>          <i>C</i>       <i>G</i>        <i>F</i>      <i>E</i>\r\n</u><u>No segundo semestre a \"depre\" atingiu o seu interior\r\n\r\n</u><u><i>G</i>              <i>F</i>         <i>C</i>   <i>G</i>        <i>F</i>       <i>E</i>\r\n</u><u>Foi duro pra ela a sua saída foi a luz do brilho\r\n\r\n</u><u>  <i>A#</i>      <i>G</i>       <i>D</i>\r\n</u><u>O branco pó alucinações rasantes\r\n\r\n</u><u><i>A#</i>           <i>G</i>              <i>A</i>\r\n</u><u>Loucuras de alto preço exorbitante\r\n\r\n</u><u><i>G</i>          <i>F</i>    <i>C</i>      <i>G</i>    <i>F</i>  <i>E</i>\r\n</u><u>Valéria a cada dia era outra\r\n\r\n</u><u><i>G</i>          <i>F</i>              <i>C</i>\r\n</u><u>Bastava a cada dia o seu pão\r\n\r\n</u><u><i>G</i>             <i>F</i>       <i>E</i>\r\n</u><u>Mas a grana bandida acabou\r\n\r\n</u><u><i>G</i>            <i>F</i>               <i>C</i>\r\n</u><u>A venda do corpo o preço do sonho\r\n\r\n</u><u><i>G</i>           <i>F</i>    <i>E</i>\r\n</u><u>Tomou-se a sua rotina\r\n\r\n</u><u><i>A#</i>            <i>G</i>          <i>D</i>\r\n</u><u>A vida não bastava seu preço solidão\r\n\r\n</u><u><i>A#</i>             <i>G</i>\r\n</u><u>Foi-lhe dada esperança\r\n\r\n</u><u>   <i>A</i>\r\n</u><u>Optou nova direção\r\n\r\n</u><u><i>G</i>     <i>F</i>              <i>C</i>\r\n</u><u>Deus Deus foi seu caminho\r\n\r\n</u><u><i>G</i>     <i>F</i>         <i>E</i>\r\n</u><u>Deus foi a sua luz\r\n\r\n</u><u><i>G</i>            <i>F</i>    <i>C</i>\r\n</u><u>Valéria uma nova vida\r\n\r\n</u><u><i>G</i>  <i>F</i>         <i>E</i>\r\n</u><u>A vida continuou\r\n\r\n\r\n</u><u>Valéria !...</u>"
}