{
  "id": "oficina-g3-davi-versao-acustica-48a50e589f",
  "title": "Davi versao acustica",
  "artist": "Oficina G3",
  "collection": "cifras_multi",
  "fileType": "html",
  "key": "G",
  "updatedAt": "2026-04-21T23:48:08.689Z",
  "html": "<u>intro: <i>Gm</i> <i>F5</i> <i>Gm</i> <i>F5</i>\r\n\r\n\r\n</u><u><i>Gm</i>                              <i>C9</i>\r\n</u><u>Os gigantes se levantam a cada dia\r\n</u><u>          <i>Bb9</i>          <i>C9</i>         <i>Gm</i>\r\n</u><u>A todo momento nos tentando destruir\r\n</u><u>                                      <i>C9</i>            <i>Bb9</i>         <i>Eb</i>\r\n</u><u>Mos gestos e no olhar buscando nos tratar ou tão somente acovardar\r\n</u><u>                 <i>D9</i>\r\n</u><u>Sem espada ou canhão\r\n</u><u>     <i>Gm</i>               <i>C9</i>              <i>Eb</i>           <i>D9</i>\r\n</u><u>Porque do senhor é a guerra que o inimigo vem ao chão\r\n</u><u>    <i>Gm</i>                   <i>F5</i>\r\n</u><u>Na força do braço de Deus\r\n\r\n</u><u>Intro.\r\n</u><u>          <i>Gm</i>\t\t\t     <i>C9</i>\r\n</u><u>Com um menino e uma pedra lançada ao ar\r\n</u><u>\t     <i>Bb9</i>       <i>C9</i>         <i>Gm</i>\r\n</u><u>É mais um Golias que vamos derrubar\r\n</u><u>\t\t\t\t   <i>C9</i>\r\n</u><u>Loucura para os homens sabedoria a Deus\r\n</u><u>           <i>Bb9</i>                  <i>Eb</i>\r\n</u><u>Esperes o Deus pra mim e pra você\r\n</u><u>                  <i>D9</i>\r\n</u><u>Sem espada ou canhão\r\n</u><u>     <i>Gm</i>                <i>C9</i>             EB           <i>D9</i>\r\n</u><u>Porque do senhor é a guerra que o inimigo vem ao chão\r\n</u><u>    <i>Gm</i>                <i>C9</i>         <i>Eb</i>         <i>D9</i>\r\n</u><u>Na força do braço de Deus sem espada ou canhão\r\n\r\n</u><u>INTRO:  <i>Gm</i>   <i>F5</i>\r\n</u><u>       <i>Eb</i>        <i>D9</i>       <i>Gm</i>                <i>C9</i>             <i>Eb</i>           <i>D9</i>\r\n</u><u>Sem espada ou canhão porque Do senhor é a guerra que o inimigo vem ao chao\r\n</u><u>    <i>Gm</i>                <i>C9</i>         <i>Eb</i>         <i>D9</i>\r\n</u><u>Na força do braço de Deus sem espada ou canhão\r\n</u><u>     <i>Gm</i>                <i>C9</i>             EB           <i>D9</i>\r\n</u><u>Porque do senhor é a guerra que o inimigo vem ao chão\r\n</u><u> <i>Gm</i>                <i>D9</i>     <i>Eb</i>        <i>C9</i>                     <i>Eb</i>            <i>D9</i>   (para em D9 e fica so a batera)\r\n</u><u>Sem espada sem canhao porque do senhor é a guerra que o inimigo vem ao chao</u>"
}