{
  "id": "renascer-praise-somos-tua-igreja-1bb0455a2d",
  "title": "Somos tua igreja",
  "artist": "Renascer Praise",
  "collection": "cifras_multi",
  "fileType": "html",
  "key": "F",
  "updatedAt": "2026-04-19T21:09:51.604Z",
  "html": "<u>Intro: <i>F</i>  <i>F7</i>  <i>Bb</i>  <i>Bm5-/7</i>\r\n</u><u>       <i>F</i>  <i>Gm</i>  <i>C</i>  <i>Bb</i>  <i>F</i>\r\n\r\n</u><u><i>F</i>       <i>Bb</i>          <i>F</i> <i>Bb</i> <i>F</i>       <i>Bb</i>      <i>F/A</i>    <i>Dm</i>     <i>Gm</i>         <i>C</i>  <i>C7</i>\r\n</u><u>Somos Tua igreja, reunida aqui.  Embaixadores do Teu reino, reino de amor.\r\n</u><u><i>F</i>               <i>Bb</i>         <i>F</i>     <i>Bb</i> <i>F</i>\r\n</u><u>De Cristo Rei dos reis, recebemos autoridade,\r\n</u><u><i>Bb</i>      <i>F</i>      <i>Dm</i>   <i>Gm</i>    <i>C</i>  <i>F</i>\r\n</u><u>estamos acima de principados e poder.\r\n</u><u>&nbsp;\r\n</u><u><i>C7</i>       <i>F</i>   <i>F7</i>          <i>Bb</i> <i>Bm5-/7</i>        <i>F</i>         <i>Dm</i>           <i>Gm</i>  <i>C</i>\r\n</u><u>Nós declaramos Jesus Tú és Senhor,      és Senhor de São Paulo e do Brasil.\r\n</u><u>   <i>C7</i>   <i>F</i>    <i>F7</i>         <i>Bb</i>  <i>B7</i>     <i>F</i>            <i>Gm</i>    <i>C</i>     <i>Bb</i>   <i>F</i>\r\n</u><u>Nós declaramos Jesus Tú és Senhor, és Senhor de São Paulo e do Brasil.\r\n</u><u>&nbsp;\r\n</u><u>1º vez volta em \"Somos tua igreja...\"\r\n</u><u>&nbsp;\r\n</u><u>      <i>Bb</i>   <i>Bbm</i>               <i>F</i>   <i>F4</i>          <i>Bb</i>       <i>Bbm</i>       <i>F</i>   <i>F7</i>\r\n</u><u>A Tí a honra,          a Tí a glória, a Tí o domínio, majestade e louvor.\r\n</u><u>      <i>Bb</i>   <i>Bbm</i>               <i>F</i>    <i>Dm</i>                  <i>Gm</i>         <i>C</i>    <i>F4</i>\r\n</u><u>A Tí a honra,          a Tí a glória,          a Tí o domínio, majestade e louvor.\r\n</u><u>&nbsp;\r\n</u><u>                                                  <i>Bb</i> <i>F</i> (<i>C#7</i>)\r\n</u><u>2º vez volta em \"Nós declaramos...\" e sobe meio tom em: (do Brasil... )\r\n</u><u>&nbsp;\r\n</u><u>  <i>C#7</i>   <i>F#</i>     <i>F#7</i>         <i>B</i> <i>Cº</i>     <i>F#</i>         <i>D#m</i>         <i>G#m</i>   <i>C#</i>\r\n</u><u>Nós declaramos Jesus Tú és Senhor, és Senhor de São Paulo e do Brasil.\r\n</u><u>  <i>C#7</i>   <i>F#</i>    <i>F#7</i>          <i>B</i> <i>Cº</i>     <i>F#</i>         <i>G#m</i>    <i>C#</i>    <i>B</i>  <i>F#</i>\r\n</u><u>Nós declaramos Jesus Tú és Senhor, és Senhor de São Paulo e do Brasil.\r\n</u><u>&nbsp;\r\n</u><u>      <i>B</i>    <i>Bm</i>             <i>F#</i> <i>F#4</i>           <i>B</i>        <i>Bm</i>        <i>F#</i>  <i>F#7</i>\r\n</u><u>A Tí a honra,       a Tí a glória, a Tí o domínio, majestade e louvor.\r\n</u><u>      <i>B</i>   <i>Bm</i>               <i>F#</i>   <i>D#m</i>                 <i>G#m</i>        <i>C#</i>    <i>F#</i>    <i>F#7</i>\r\n</u><u>A Tí a honra,        a Tí a glória,          a Tí o domínio, majestade    e    louvor.\r\n</u><u>         <i>B</i>         <i>G#m</i>   <i>C#</i>       <i>F#</i>     <i>D#m</i>\r\n</u><u>a Tí o domínio, majestade    e    louvor... (repete e fim (hino do Brasil) )</u>"
}