{
  "id": "vencedores-por-cristo-nada-melhor-2561007405",
  "title": "Nada melhor",
  "artist": "Vencedores Por Cristo",
  "collection": "cifras_multi",
  "fileType": "html",
  "key": "D",
  "updatedAt": "2026-04-27T00:57:29.930Z",
  "html": "<u><i>D#</i>               <i>A#</i>       <i>Cm</i>          <i>Fm</i>          <i>A#</i>         <i>D#</i>\r\n</u><u>Muito embora, um só Jesus exista, nem todos sabem vê-lo como é.\r\n</u><u><i>Fm</i>          <i>G#°</i>       <i>Cm</i>         <i>Fm</i>               <i>A#</i>           <i>D#</i>\r\n</u><u>Filósofo, poeta ou comunista, ou mesmo um hippie, já se disse até.\r\n</u><u><i>D#</i>           <i>A#</i>       <i>Cm</i>          <i>Fm</i>               <i>A#</i>          <i>D#</i>\r\n</u><u>Mas, Jesus é bem mais importante, quando se sabe de Seu grande amor.\r\n</u><u>  <i>Fm</i>         <i>G#°</i>          <i>Cm</i>       <i>Fm</i>            <i>A#</i>           <i>D#</i>\r\n</u><u>E é preciso, hoje, que se cante, Jesus, Filho de Deus, o Salvador!\r\n\r\n</u><u>         <i>D#</i>         <i>Fm</i>\r\n</u><u>Por todo mundo procurei,\r\n</u><u>         <i>D#</i>              <i>A#</i>\r\n</u><u>Verdade e amor com que sonhei;\r\n</u><u>       <i>D#</i>           <i>Fm</i>\r\n</u><u>Vazio achei ao meu redor,\r\n</u><u><i>D#</i>    <i>A#</i>            <i>Cm</i>\r\n</u><u>Nada melhor. Nada melhor.\r\n\r\n</u><u>         <i>D#</i>     <i>Fm</i>                     <i>D#</i>            <i>A#</i>\r\n</u><u>Ao ver a vida se perder, tão fraco, eu penso em que fazer,\r\n</u><u>            <i>D#</i>        <i>Fm</i>          <i>D#</i>    <i>A#</i>\r\n</u><u>Quem vem trazer a solução da direção? Da direção?\r\n</u><u>         <i>Cm</i>\r\n</u><u>Da direção...\r\n\r\n</u><u>      <i>Fm</i>           <i>Cm</i>            <i>Fm</i>           <i>Cm</i>\r\n</u><u>Tanta procura e ilusão, a vida escura e sem razão.\r\n</u><u>        <i>Fm</i>           <i>Cm</i>\r\n</u><u>Viver a troco de não ser, melhor morrer, melhor morrer.\r\n</u><u>          <i>C</i>  <i>Cm</i>\r\n</u><u>Melhor morrer...\r\n\r\n</u><u>          <i>D#</i>              <i>Fm</i>              <i>D#</i>              <i>A#</i>\r\n</u><u>Caminho estreito, eu vi a cruz, e no meu peito o céu em luz.\r\n</u><u>             <i>D#</i>           <i>Fm</i>       <i>D#</i>     <i>A#</i>\r\n</u><u>Meu sonho, a paz, achei enfim, Jesus em mim!\r\n</u><u>         <i>D#</i>  <i>Fm</i>\r\n</u><u>Jesus em mim!   (3x)\r\n</u><u>          <i>Fm</i>\r\n</u><u>Jesus em mim!</u>"
}